helloworld/__init__.py
helloworld/main.py
renesy_helloworld-0.1.4.dist-info/METADATA
renesy_helloworld-0.1.4.dist-info/WHEEL
renesy_helloworld-0.1.4.dist-info/entry_points.txt
renesy_helloworld-0.1.4.dist-info/top_level.txt
renesy_helloworld-0.1.4.dist-info/RECORD
